MdnCanvasApiZhongwenWendang20171202/README.md
MdnCanvasApiZhongwenWendang20171202/__init__.py
MdnCanvasApiZhongwenWendang20171202/__main__.py
MdnCanvasApiZhongwenWendang20171202/file.epub
MdnCanvasApiZhongwenWendang20171202/index.html
MdnCanvasApiZhongwenWendang20171202/css/__init__.py
MdnCanvasApiZhongwenWendang20171202/css/annotations.css
MdnCanvasApiZhongwenWendang20171202/css/main.css
MdnCanvasApiZhongwenWendang20171202/css/normalize.css
MdnCanvasApiZhongwenWendang20171202/css/popup.css
MdnCanvasApiZhongwenWendang20171202/font/__init__.py
MdnCanvasApiZhongwenWendang20171202/font/fontello.eot
MdnCanvasApiZhongwenWendang20171202/font/fontello.svg
MdnCanvasApiZhongwenWendang20171202/font/fontello.ttf
MdnCanvasApiZhongwenWendang20171202/font/fontello.woff
MdnCanvasApiZhongwenWendang20171202/img/__init__.py
MdnCanvasApiZhongwenWendang20171202/img/annotator-glyph-sprite.png
MdnCanvasApiZhongwenWendang20171202/img/annotator-icon-sprite.png
MdnCanvasApiZhongwenWendang20171202/img/apple-touch-icon.png
MdnCanvasApiZhongwenWendang20171202/img/cancelfullscreen.png
MdnCanvasApiZhongwenWendang20171202/img/close.png
MdnCanvasApiZhongwenWendang20171202/img/fullscreen.png
MdnCanvasApiZhongwenWendang20171202/img/loader.gif
MdnCanvasApiZhongwenWendang20171202/img/menu-icon.png
MdnCanvasApiZhongwenWendang20171202/img/save.png
MdnCanvasApiZhongwenWendang20171202/img/saved.png
MdnCanvasApiZhongwenWendang20171202/img/settings-s.png
MdnCanvasApiZhongwenWendang20171202/img/settings.png
MdnCanvasApiZhongwenWendang20171202/img/star.png
MdnCanvasApiZhongwenWendang20171202/js/__init__.py
MdnCanvasApiZhongwenWendang20171202/js/epub.js
MdnCanvasApiZhongwenWendang20171202/js/epub.min.js
MdnCanvasApiZhongwenWendang20171202/js/epub.min.map
MdnCanvasApiZhongwenWendang20171202/js/hooks.min.js
MdnCanvasApiZhongwenWendang20171202/js/hooks.min.map
MdnCanvasApiZhongwenWendang20171202/js/reader.js
MdnCanvasApiZhongwenWendang20171202/js/reader.js.map
MdnCanvasApiZhongwenWendang20171202/js/reader.min.js
mdn_canvas_api_zhongwen_wendang_20171202-2024.3.2.0.dist-info/METADATA
mdn_canvas_api_zhongwen_wendang_20171202-2024.3.2.0.dist-info/WHEEL
mdn_canvas_api_zhongwen_wendang_20171202-2024.3.2.0.dist-info/entry_points.txt
mdn_canvas_api_zhongwen_wendang_20171202-2024.3.2.0.dist-info/top_level.txt
mdn_canvas_api_zhongwen_wendang_20171202-2024.3.2.0.dist-info/RECORD
